README.md
setup.py
auth/__init__.py
auth/config.py
auth/main.py
tda-vol/__init__.py
tda-vol/scripts/__init__.py
tda-vol/scripts/blackscholes.py
tda-vol/scripts/fundamental.py
tda-vol/scripts/iv_screener.py
tda-vol/scripts/ivx.py
tda-vol/scripts/option_chain.py
tda_vol.egg-info/PKG-INFO
tda_vol.egg-info/SOURCES.txt
tda_vol.egg-info/dependency_links.txt
tda_vol.egg-info/requires.txt
tda_vol.egg-info/top_level.txt